travrse/__init__.py
travrse/_utils.py
travrse/client.py
travrse/exceptions.py
travrse/flow_builder.py
travrse/py.typed
travrse/runtype.py
travrse/types.py
travrse/resources/__init__.py
travrse/resources/flows.py
travrse/resources/prompts.py
travrse/resources/records.py
travrse-0.1.1.dist-info/METADATA
travrse-0.1.1.dist-info/WHEEL
travrse-0.1.1.dist-info/licenses/LICENSE
travrse-0.1.1.dist-info/RECORD
